multiviewdata/__init__.py
multiviewdata/tasks/__init__.py
multiviewdata/test/__init__.py
multiviewdata/test/test_outputs.py
multiviewdata/torchdatasets/__init__.py
multiviewdata/torchdatasets/cars3d.py
multiviewdata/torchdatasets/cub.py
multiviewdata/torchdatasets/generic.py
multiviewdata/torchdatasets/mediamill.py
multiviewdata/torchdatasets/mfeat.py
multiviewdata/torchdatasets/mirflickr.py
multiviewdata/torchdatasets/mnist.py
multiviewdata/torchdatasets/tgca.py
multiviewdata/torchdatasets/twitter.py
multiviewdata/torchdatasets/utils.py
multiviewdata/torchdatasets/wiw.py
multiviewdata/torchdatasets/xrmb.py
multiviewdata/torchmodels/__init__.py
multiviewdata/torchmodels/cars3d.py
multiviewdata/torchmodels/cub.py
multiviewdata/torchmodels/mfeat.py
multiviewdata/torchmodels/mnist.py
multiviewdata/torchmodels/twitter.py
multiviewdata/torchmodels/wiw.py
multiviewdata/torchmodels/xrmb.py
multiviewdata/utils/__init__.py
multiviewdata-0.7.dist-info/LICENSE
multiviewdata-0.7.dist-info/METADATA
multiviewdata-0.7.dist-info/WHEEL
multiviewdata-0.7.dist-info/top_level.txt
multiviewdata-0.7.dist-info/RECORD
