Metadata-Version: 2.1
Name: multiviewdata
Version: 0.7
Summary: Packaged data modules for multiview learning benchmarks
Home-page: UNKNOWN
Author: James Chapman
Author-email: james.chapman.19@ucl.ac.uk
License: UNKNOWN
Platform: UNKNOWN
Requires-Dist: torch (>=1.9.0)
Requires-Dist: torchvision
Requires-Dist: Pillow
Requires-Dist: numpy
Requires-Dist: scipy
Requires-Dist: h5py
Requires-Dist: matplotlib
Requires-Dist: nltk
Requires-Dist: pandas
